pyquotegen/__init__.py
pyquotegen/all_quotes.py
pyquotegen-0.0.4.dist-info/LICENSE
pyquotegen-0.0.4.dist-info/METADATA
pyquotegen-0.0.4.dist-info/WHEEL
pyquotegen-0.0.4.dist-info/top_level.txt
pyquotegen-0.0.4.dist-info/RECORD
