Metadata-Version: 2.1
Name: pyquotegen
Version: 0.0.4
Summary: A Random Quote Generator Python Package
Home-page: https://github.com/Armanidrisi/pyquotegen
Author: Arman Idrisi
Author-email: idrisiarman19@gmail.com
Project-URL: Bug Tracker, https://github.com/Armanidrisi/pyquotegen/issues
Project-URL: Documentation, https://github.com/Armanidrisi/pyquotegen/blob/main/README.md
Project-URL: Source Code, https://github.com/Armanidrisi/pyquotegen
Classifier: Programming Language :: Python :: 3
Classifier: License :: OSI Approved :: MIT License
Classifier: Operating System :: OS Independent
Classifier: Intended Audience :: Developers
Classifier: Topic :: Software Development :: Libraries :: Python Modules
Requires-Python: >=3.0
License-File: LICENSE
